{"cameraMode":{"drawMode":0,"name":"Shaded","section":"Shading Mode"},"sceneLighting":true,"audioPlay":false,"sceneViewState":{"m_AlwaysRefresh":false,"showFog":true,"showSkybox":true,"showFlares":true,"showImageEffects":true,"showParticleSystems":true,"showVisualEffectGraphs":true,"m_FxEnabled":true},"in2DMode":false,"pivot":{"x":0.49224230647087099,"y":33.80443572998047,"z":-37.696388244628909},"rotation":{"x":-0.41025006771087649,"y":0.03364364057779312,"z":-0.01513583492487669,"w":-0.9112893342971802},"size":17.53981590270996,"orthographic":false}